profit_sniper_protocols/__init__.py
profit_sniper_protocols/py.typed
profit_sniper_protocols-0.1.10.dist-info/METADATA
profit_sniper_protocols-0.1.10.dist-info/WHEEL
profit_sniper_protocols-0.1.10.dist-info/RECORD
