Metadata-Version: 2.3
Name: profit-sniper-protocols
Version: 0.1.10
Summary: Protocol definitions for the Profit Sniper Trading app plugins.
Author-email: Takin Profit LLC <takinprofit@gmail.com>
License: MIT License
Requires-Python: >=3.12
Requires-Dist: pydantic>=2.9.2
